[
null,
{"id":1,"expanded":false,"name":"Cat Puzzle ","order":4,"parentId":3,"scrollX":771,"scrollY":531.75},
{"id":2,"expanded":false,"name":"Classroom","order":1,"parentId":0,"scrollX":832,"scrollY":640},
{"id":3,"expanded":true,"name":"TA Encounter","order":5,"parentId":4,"scrollX":771,"scrollY":531.75},
{"id":4,"expanded":true,"name":"Snow Level","order":3,"parentId":0,"scrollX":816,"scrollY":800},
{"id":5,"expanded":false,"name":"Hallway","order":2,"parentId":0,"scrollX":771,"scrollY":531.75},
{"id":6,"expanded":true,"name":"Bio-Sci","order":6,"parentId":0,"scrollX":771,"scrollY":531.75},
{"id":7,"expanded":false,"name":"Horizontal_Hallway","order":14,"parentId":6,"scrollX":771,"scrollY":531.75},
{"id":8,"expanded":false,"name":"Elbow_2","order":9,"parentId":6,"scrollX":771,"scrollY":531.75},
{"id":9,"expanded":false,"name":"Elbow_1","order":8,"parentId":6,"scrollX":771,"scrollY":531.75},
{"id":10,"expanded":false,"name":"Left_T_Junction","order":13,"parentId":6,"scrollX":771,"scrollY":531.75},
{"id":11,"expanded":false,"name":"Dead_End_1","order":7,"parentId":6,"scrollX":771,"scrollY":531.75},
{"id":12,"expanded":true,"name":"Elbow_3","order":10,"parentId":6,"scrollX":771,"scrollY":531.75},
{"id":13,"expanded":false,"name":"Elbow_4","order":11,"parentId":6,"scrollX":771,"scrollY":531.75},
{"id":14,"expanded":false,"name":"Right_T_Junction","order":12,"parentId":6,"scrollX":771,"scrollY":531.75},
{"id":15,"expanded":false,"name":"Vertical_Hallway","order":15,"parentId":6,"scrollX":832,"scrollY":640}
]